persist_spatial/__init__.py
persist_spatial/compute_persistence.py
persist_spatial/network_functions.py
persist_spatial/plotting_utils.py
persist_spatial/post_ph_functions.py
persist_spatial/smoothed_expression.py
persist_spatial/topology_utils.py
persist_spatial/.ipynb_checkpoints/compute_persistence-checkpoint.py
persist_spatial/.ipynb_checkpoints/network_functions-checkpoint.py
persist_spatial/.ipynb_checkpoints/plotting_utils-checkpoint.py
persist_spatial/.ipynb_checkpoints/post_ph_functions-checkpoint.py
persist_spatial/.ipynb_checkpoints/smoothed_expression-checkpoint.py
persist_spatial/.ipynb_checkpoints/topology_utils-checkpoint.py
persist_spatial-0.1.0.dist-info/METADATA
persist_spatial-0.1.0.dist-info/WHEEL
persist_spatial-0.1.0.dist-info/licenses/LICENSE
persist_spatial-0.1.0.dist-info/RECORD
