Metadata-Version: 2.4
Name: persist_spatial
Version: 0.1.0
Summary: A package for computation of continuous spatial structure scores in spatial omics data.
Author-email: James Boyle <james.boyle@maths.ox.ac.uk>
License-Expression: Apache-2.0
License-File: LICENSE
Classifier: Operating System :: OS Independent
Classifier: Programming Language :: Python :: 3
Requires-Python: >=3.9
Requires-Dist: dionysus>=2.0.10
Requires-Dist: kneed>=0.8.5
Requires-Dist: matplotlib>=3.8.0
Requires-Dist: numpy>=1.26.2
Requires-Dist: pandas>=2.1.4
Requires-Dist: scikit-learn>=1.3.0
Requires-Dist: scipy>=1.11.4
Requires-Dist: seaborn>=0.12.2
